basepy/__init__.py
basepy/abis.py
basepy/client.py
basepy/contracts.py
basepy/exceptions.py
basepy/standards.py
basepy/transactions.py
basepy/utils.py
basepy/wallet.py
basepy_sdk-1.1.0.dist-info/licenses/LICENSE
basepy_sdk-1.1.0.dist-info/METADATA
basepy_sdk-1.1.0.dist-info/WHEEL
basepy_sdk-1.1.0.dist-info/top_level.txt
basepy_sdk-1.1.0.dist-info/RECORD
