Metadata-Version: 2.4
Name: basepy-sdk
Version: 1.1.0
Summary: Production-ready Python SDK for Base blockchain with 80% fewer RPC calls, zero-cost ERC-20 decoding, and built-in resilience
Home-page: https://github.com/basepy/basepy-sdk
Author: BasePy Team
Author-email: BasePy Team <support@basepy.dev>
Maintainer: BasePy Team
Maintainer-email: BasePy Team <support@basepy.dev>
Project-URL: Homepage, https://github.com/yourusername/basepy-sdk
Project-URL: Documentation, https://github.com/yourusername/basepy-sdk/blob/main/README.md
Project-URL: Repository, https://github.com/yourusername/basepy-sdk
Project-URL: Bug Tracker, https://github.com/yourusername/basepy-sdk/issues
Project-URL: Source Code, https://github.com/yourusername/basepy-sdk
Project-URL: Changelog, https://github.com/yourusername/basepy-sdk/blob/main/CHANGELOG.md
Keywords: base,blockchain,ethereum,layer2,l2,web3,crypto,defi,erc20,wallet,transaction,smart-contracts,rpc,optimism,op-stack
Classifier: Development Status :: 4 - Beta
Classifier: Intended Audience :: Developers
Classifier: Topic :: Software Development :: Libraries :: Python Modules
Classifier: Topic :: Internet
Classifier: Topic :: System :: Networking
Classifier: Programming Language :: Python :: 3
Classifier: Programming Language :: Python :: 3.8
Classifier: Programming Language :: Python :: 3.9
Classifier: Programming Language :: Python :: 3.10
Classifier: Programming Language :: Python :: 3.11
Classifier: Programming Language :: Python :: 3.12
Classifier: Operating System :: OS Independent
Classifier: Typing :: Typed
Requires-Python: >=3.8
License-File: LICENSE
Requires-Dist: web3<7.0.0,>=6.0.0
Requires-Dist: eth-account>=0.9.0
Requires-Dist: eth-utils>=2.0.0
Provides-Extra: dev
Requires-Dist: pytest>=7.0.0; extra == "dev"
Requires-Dist: pytest-cov>=4.0.0; extra == "dev"
Requires-Dist: pytest-asyncio>=0.21.0; extra == "dev"
Requires-Dist: pytest-benchmark>=4.0.0; extra == "dev"
Requires-Dist: black>=23.0.0; extra == "dev"
Requires-Dist: flake8>=6.0.0; extra == "dev"
Requires-Dist: mypy>=1.0.0; extra == "dev"
Requires-Dist: isort>=5.12.0; extra == "dev"
Requires-Dist: pre-commit>=3.0.0; extra == "dev"
Provides-Extra: docs
Requires-Dist: sphinx>=5.0.0; extra == "docs"
Requires-Dist: sphinx-rtd-theme>=1.2.0; extra == "docs"
Requires-Dist: sphinx-autodoc-typehints>=1.23.0; extra == "docs"
Requires-Dist: myst-parser>=1.0.0; extra == "docs"
Provides-Extra: test
Requires-Dist: pytest>=7.0.0; extra == "test"
Requires-Dist: pytest-cov>=4.0.0; extra == "test"
Requires-Dist: pytest-asyncio>=0.21.0; extra == "test"
Requires-Dist: pytest-benchmark>=4.0.0; extra == "test"
Requires-Dist: tox>=4.0.0; extra == "test"
Provides-Extra: all
Requires-Dist: basepy-sdk[dev,docs,test]; extra == "all"
Dynamic: author
Dynamic: home-page
Dynamic: license-file
Dynamic: maintainer
Dynamic: requires-python
